lztools/lmod.py
lztools/modules.py
lztools.modules-1.0.0.dist-info/LICENSE.txt
lztools.modules-1.0.0.dist-info/METADATA
lztools.modules-1.0.0.dist-info/RECORD
lztools.modules-1.0.0.dist-info/WHEEL
lztools.modules-1.0.0.dist-info/entry_points.txt
lztools.modules-1.0.0.dist-info/top_level.txt
