Metadata-Version: 2.1
Name: lztools.modules
Version: 1.0.0
Summary: A collection of useful utilities by Laz aka Zanzes
Home-page: UNKNOWN
Author: Laz aka Zanzes
Author-email: ubuntuea@gmail.com
License: MIT License
Platform: UNKNOWN
Classifier: Development Status :: 3 - Alpha
Classifier: Intended Audience :: Developers
Classifier: Topic :: System :: Systems Administration
Classifier: License :: OSI Approved :: MIT License
Classifier: Programming Language :: Python :: 3.7
Requires-Dist: click
